setup.py
django_favorites.egg-info/PKG-INFO
django_favorites.egg-info/SOURCES.txt
django_favorites.egg-info/dependency_links.txt
django_favorites.egg-info/top_level.txt
favorites/__init__.py
favorites/admin.py
favorites/models.py
favorites/tests.py
favorites/views.py
favorites/templatetags/__init__.py
favorites/templatetags/favorite_tags.py