Metadata-Version: 1.0
Name: django-favorites
Version: 0.1
Summary: favorites app for django
Home-page: https://github.com/jeffkit/django-favorites
Author: jeff kit
Author-email: bbmyth@gmail.com
License: UNKNOWN
Platform: UNKNOWN
